edc_model_admin/__init__.py
edc_model_admin/admin_site.py
edc_model_admin/apps.py
edc_model_admin/context_processors.py
edc_model_admin/system_checks.py
edc_model_admin/utils.py
edc_model_admin/changelist_buttons/__init__.py
edc_model_admin/changelist_buttons/model_admin_changelist_button_mixin.py
edc_model_admin/changelist_buttons/model_admin_changelist_model_button_mixin.py
edc_model_admin/dashboard/__init__.py
edc_model_admin/dashboard/model_admin_crf_dashboard_mixin.py
edc_model_admin/dashboard/model_admin_dashboard_mixin.py
edc_model_admin/dashboard/model_admin_stacked_inline_mixin.py
edc_model_admin/dashboard/model_admin_subject_dashboard_mixin.py
edc_model_admin/history/__init__.py
edc_model_admin/history/model_admin_simple_history.py
edc_model_admin/list_filters/__init__.py
edc_model_admin/list_filters/future_date_list_filter.py
edc_model_admin/list_filters/list_field_with_other_list_filter.py
edc_model_admin/list_filters/past_date_list_filter.py
edc_model_admin/list_filters/report_date_list_filter.py
edc_model_admin/locale/lg/LC_MESSAGES/django.mo
edc_model_admin/locale/lg/LC_MESSAGES/django.po
edc_model_admin/locale/sw/LC_MESSAGES/django.mo
edc_model_admin/locale/sw/LC_MESSAGES/django.po
edc_model_admin/mixins/__init__.py
edc_model_admin/mixins/address_model_admin_mixin.py
edc_model_admin/mixins/base_model_admin_redirect_mixin.py
edc_model_admin/mixins/model_admin_bypass_default_form_cls_mixin.py
edc_model_admin/mixins/model_admin_form_auto_number_mixin.py
edc_model_admin/mixins/model_admin_form_instructions_mixin.py
edc_model_admin/mixins/model_admin_hide_delete_button_on_condition.py
edc_model_admin/mixins/model_admin_institution_mixin.py
edc_model_admin/mixins/model_admin_limit_to_selected_foreignkey.py
edc_model_admin/mixins/model_admin_model_redirect_mixin.py
edc_model_admin/mixins/model_admin_next_url_redirect_mixin.py
edc_model_admin/mixins/model_admin_protect_pii_mixin.py
edc_model_admin/mixins/model_admin_redirect_all_to_changelist_mixin.py
edc_model_admin-1.0.3.dist-info/licenses/AUTHORS.rst
edc_model_admin-1.0.3.dist-info/licenses/LICENSE
edc_model_admin-1.0.3.dist-info/METADATA
edc_model_admin-1.0.3.dist-info/WHEEL
edc_model_admin-1.0.3.dist-info/top_level.txt
edc_model_admin-1.0.3.dist-info/RECORD
